qiskitflow/__init__.py
qiskitflow/_version.py
qiskitflow/cli/__init__.py
qiskitflow/cli/cli.py
qiskitflow/cli/runs/__init__.py
qiskitflow/cli/runs/detail.py
qiskitflow/cli/runs/experiments.py
qiskitflow/cli/runs/list.py
qiskitflow/cli/runs/share.py
qiskitflow/lib/__init__.py
qiskitflow/lib/experiment.py
qiskitflow/lib/models/__init__.py
qiskitflow/lib/models/artifact.py
qiskitflow/lib/models/counts.py
qiskitflow/lib/models/metric.py
qiskitflow/lib/models/parameter.py
qiskitflow/lib/models/state_vector.py
qiskitflow/utils/__init__.py
qiskitflow/utils/constants.py
qiskitflow/utils/utils.py
tests/__init__.py
tests/cli/__init__.py
tests/cli/runs/__init__.py
tests/cli/runs/test_info.py
tests/cli/runs/test_list.py
tests/lib/__init__.py
tests/lib/test_experiment.py
qiskitflow-0.0.11a0.dist-info/METADATA
qiskitflow-0.0.11a0.dist-info/WHEEL
qiskitflow-0.0.11a0.dist-info/entry_points.txt
qiskitflow-0.0.11a0.dist-info/top_level.txt
qiskitflow-0.0.11a0.dist-info/RECORD
