Metadata-Version: 2.1
Name: qiskitflow
Version: 0.0.11a0
Summary: QiskitFlow. Reproducible quantum experiments.
Home-page: https://github.com/IceKhan13/QiskitFlow
Author: Iskandar Sitdikov
Author-email: iskandar.sitdikov@gmail.com
License: Apache 2.0
Keywords: quantum computing,qiskit,experiments,reproducibility,tracking
Platform: UNKNOWN
Classifier: License :: OSI Approved :: Apache Software License
Classifier: Operating System :: MacOS
Classifier: Operating System :: POSIX :: Linux
Classifier: Programming Language :: Python :: 3
Classifier: Programming Language :: Python :: 3.6
Classifier: Programming Language :: Python :: 3.7
Classifier: Topic :: Scientific/Engineering
Requires-Python: >=3.6
